MANIFEST.in
README.md
setup.py
Brat.egg-info/PKG-INFO
Brat.egg-info/SOURCES.txt
Brat.egg-info/dependency_links.txt
Brat.egg-info/entry_points.txt
Brat.egg-info/not-zip-safe
Brat.egg-info/requires.txt
Brat.egg-info/top_level.txt
brat/__init__.py
brat/authenticate.py
brat/convert.py
brat/handler.py
brat/macro.py
brat/paginator.py
brat/serializers.py
brat/utils.py
brat/exception/__init__.py
brat/exception/exceptions.py
brat/exception/handler.py
doc_generator/__init__.py
doc_generator/doc.py
tests/__init__.py
tests/test_views.py